metaflow-stubs/__init__.pyi
metaflow-stubs/cards.pyi
metaflow-stubs/cli.pyi
metaflow-stubs/events.pyi
metaflow-stubs/exception.pyi
metaflow-stubs/flowspec.pyi
metaflow-stubs/generated_for.txt
metaflow-stubs/includefile.pyi
metaflow-stubs/meta_files.pyi
metaflow-stubs/metaflow_config.pyi
metaflow-stubs/metaflow_current.pyi
metaflow-stubs/metaflow_git.pyi
metaflow-stubs/multicore_utils.pyi
metaflow-stubs/parameters.pyi
metaflow-stubs/py.typed
metaflow-stubs/pylint_wrapper.pyi
metaflow-stubs/tagging_util.pyi
metaflow-stubs/tuple_util.pyi
metaflow-stubs/version.pyi
metaflow-stubs/cli_components/__init__.pyi
metaflow-stubs/cli_components/utils.pyi
metaflow-stubs/client/__init__.pyi
metaflow-stubs/client/core.pyi
metaflow-stubs/client/filecache.pyi
metaflow-stubs/metadata_provider/__init__.pyi
metaflow-stubs/metadata_provider/heartbeat.pyi
metaflow-stubs/metadata_provider/metadata.pyi
metaflow-stubs/metadata_provider/util.pyi
metaflow-stubs/packaging_sys/__init__.pyi
metaflow-stubs/packaging_sys/backend.pyi
metaflow-stubs/packaging_sys/distribution_support.pyi
metaflow-stubs/packaging_sys/tar_backend.pyi
metaflow-stubs/packaging_sys/utils.pyi
metaflow-stubs/packaging_sys/v1.pyi
metaflow-stubs/plugins/__init__.pyi
metaflow-stubs/plugins/catch_decorator.pyi
metaflow-stubs/plugins/debug_logger.pyi
metaflow-stubs/plugins/debug_monitor.pyi
metaflow-stubs/plugins/environment_decorator.pyi
metaflow-stubs/plugins/events_decorator.pyi
metaflow-stubs/plugins/parallel_decorator.pyi
metaflow-stubs/plugins/parsers.pyi
metaflow-stubs/plugins/project_decorator.pyi
metaflow-stubs/plugins/resources_decorator.pyi
metaflow-stubs/plugins/retry_decorator.pyi
metaflow-stubs/plugins/storage_executor.pyi
metaflow-stubs/plugins/test_unbounded_foreach_decorator.pyi
metaflow-stubs/plugins/timeout_decorator.pyi
metaflow-stubs/plugins/airflow/__init__.pyi
metaflow-stubs/plugins/airflow/airflow_decorator.pyi
metaflow-stubs/plugins/airflow/airflow_utils.pyi
metaflow-stubs/plugins/airflow/exception.pyi
metaflow_stubs-2.19.15.dist-info/METADATA
metaflow_stubs-2.19.15.dist-info/WHEEL
metaflow_stubs-2.19.15.dist-info/top_level.txt
metaflow_stubs-2.19.15.dist-info/RECORD
